odoo/addons/l10n_mx_res_partner_csf/README.rst
odoo/addons/l10n_mx_res_partner_csf/__init__.py
odoo/addons/l10n_mx_res_partner_csf/__manifest__.py
odoo/addons/l10n_mx_res_partner_csf/i18n/l10n_mx_res_partner_csf.pot
odoo/addons/l10n_mx_res_partner_csf/models/__init__.py
odoo/addons/l10n_mx_res_partner_csf/models/res_partner.py
odoo/addons/l10n_mx_res_partner_csf/readme/CONTRIBUTORS.md
odoo/addons/l10n_mx_res_partner_csf/readme/CREDITS.md
odoo/addons/l10n_mx_res_partner_csf/readme/DESCRIPTION.md
odoo/addons/l10n_mx_res_partner_csf/readme/INSTALL.md
odoo/addons/l10n_mx_res_partner_csf/readme/USAGE.md
odoo/addons/l10n_mx_res_partner_csf/security/ir.model.access.csv
odoo/addons/l10n_mx_res_partner_csf/static/description/icon.png
odoo/addons/l10n_mx_res_partner_csf/static/description/index.html
odoo/addons/l10n_mx_res_partner_csf/tests/__init__.py
odoo/addons/l10n_mx_res_partner_csf/tests/demo.pdf
odoo/addons/l10n_mx_res_partner_csf/tests/test_contact.py
odoo/addons/l10n_mx_res_partner_csf/views/res_partner_view.xml
odoo/addons/l10n_mx_res_partner_csf/wizard/__init__.py
odoo/addons/l10n_mx_res_partner_csf/wizard/import_csf.py
odoo/addons/l10n_mx_res_partner_csf/wizard/import_csf.xml
odoo_addon_l10n_mx_res_partner_csf-17.0.1.1.0.dist-info/METADATA
odoo_addon_l10n_mx_res_partner_csf-17.0.1.1.0.dist-info/WHEEL
odoo_addon_l10n_mx_res_partner_csf-17.0.1.1.0.dist-info/top_level.txt
odoo_addon_l10n_mx_res_partner_csf-17.0.1.1.0.dist-info/RECORD
