Metadata-Version: 2.1
Name: odoo-addon-l10n_mx_res_partner_csf
Version: 17.0.1.1.0
Requires-Python: >=3.10
Requires-Dist: odoo>=17.0a,<17.1dev
Requires-Dist: pdfminer.six==20220319
Summary: Scan and extract information from CSF
Home-page: https://github.com/OCA/l10n-mexico
License: AGPL-3
Author: Open Source Integrators, Odoo Community Association (OCA)
Author-email: support@odoo-community.org
Classifier: Programming Language :: Python
Classifier: Framework :: Odoo
Classifier: Framework :: Odoo :: 17.0
Classifier: License :: OSI Approved :: GNU Affero General Public License v3
